{
  "type" : "CodegenReports",
  "reports" : {
    "type" : "Map",
    "entries" : [
      [
        "KEY_TOOL_REPORT",
        {
          "type" : "ToolReport",
          "commandLineArgs" : "<empty-arguments>",
          "status" : {
            "type" : "Status",
            "value" : "Success"
          },
          "warningMessages" : [
          ],
          "errorMessages" : [
          ],
          "resources" : [
            {
              "type" : "ResourceReport",
              "path" : "types\/include\/sb_aadl_types.h",
              "overwrittenIfExists" : true
            },
            {
              "type" : "ResourceReport",
              "path" : "types\/include\/sb_event_counter.h",
              "overwrittenIfExists" : true
            },
            {
              "type" : "ResourceReport",
              "path" : "types\/include\/sb_queue_Gumbo_Structs_Arrays_MyStructArray_i_1.h",
              "overwrittenIfExists" : true
            },
            {
              "type" : "ResourceReport",
              "path" : "types\/src\/sb_queue_Gumbo_Structs_Arrays_MyStructArray_i_1.c",
              "overwrittenIfExists" : true
            },
            {
              "type" : "ResourceReport",
              "path" : "types\/include\/sb_queue_Gumbo_Structs_Arrays_MyArrayStruct_1.h",
              "overwrittenIfExists" : true
            },
            {
              "type" : "ResourceReport",
              "path" : "types\/src\/sb_queue_Gumbo_Structs_Arrays_MyArrayStruct_1.c",
              "overwrittenIfExists" : true
            },
            {
              "type" : "ResourceReport",
              "path" : "types\/include\/sb_queue_Gumbo_Structs_Arrays_MyArrayInt32_1.h",
              "overwrittenIfExists" : true
            },
            {
              "type" : "ResourceReport",
              "path" : "types\/src\/sb_queue_Gumbo_Structs_Arrays_MyArrayInt32_1.c",
              "overwrittenIfExists" : true
            },
            {
              "type" : "ResourceReport",
              "path" : "types\/include\/sb_types.h",
              "overwrittenIfExists" : true
            },
            {
              "type" : "ResourceReport",
              "path" : "components\/producer_producer\/src\/producer_producer_MON.c",
              "overwrittenIfExists" : true
            },
            {
              "type" : "ResourceReport",
              "path" : "components\/producer_producer\/src\/producer_producer.c",
              "overwrittenIfExists" : true
            },
            {
              "type" : "ResourceReport",
              "path" : "components\/producer_producer\/src\/producer_producer_user.c",
              "overwrittenIfExists" : false
            },
            {
              "type" : "ResourceReport",
              "path" : "components\/producer_producer\/include\/producer_producer.h",
              "overwrittenIfExists" : true
            },
            {
              "type" : "ResourceReport",
              "path" : "components\/consumer_consumer\/src\/consumer_consumer_MON.c",
              "overwrittenIfExists" : true
            },
            {
              "type" : "ResourceReport",
              "path" : "components\/consumer_consumer\/src\/consumer_consumer.c",
              "overwrittenIfExists" : true
            },
            {
              "type" : "ResourceReport",
              "path" : "components\/consumer_consumer\/src\/consumer_consumer_user.c",
              "overwrittenIfExists" : false
            },
            {
              "type" : "ResourceReport",
              "path" : "components\/consumer_consumer\/include\/consumer_consumer.h",
              "overwrittenIfExists" : true
            },
            {
              "type" : "ResourceReport",
              "path" : "components\/pacer\/src\/pacer.c",
              "overwrittenIfExists" : true
            },
            {
              "type" : "ResourceReport",
              "path" : "microkit.system",
              "overwrittenIfExists" : false
            },
            {
              "type" : "ResourceReport",
              "path" : "microkit.schedule.xml",
              "overwrittenIfExists" : false
            },
            {
              "type" : "ResourceReport",
              "path" : "microkit.dot",
              "overwrittenIfExists" : true
            },
            {
              "type" : "ResourceReport",
              "path" : "Makefile",
              "overwrittenIfExists" : true
            },
            {
              "type" : "ResourceReport",
              "path" : "system.mk",
              "overwrittenIfExists" : true
            },
            {
              "type" : "ResourceReport",
              "path" : "util\/include\/printf.h",
              "overwrittenIfExists" : true
            },
            {
              "type" : "ResourceReport",
              "path" : "util\/src\/printf.c",
              "overwrittenIfExists" : true
            },
            {
              "type" : "ResourceReport",
              "path" : "util\/include\/util.h",
              "overwrittenIfExists" : true
            },
            {
              "type" : "ResourceReport",
              "path" : "util\/src\/util.c",
              "overwrittenIfExists" : true
            },
            {
              "type" : "ResourceReport",
              "path" : "crates\/data\/src\/Gumbo_Structs_Arrays\/MyEnum.rs",
              "overwrittenIfExists" : true
            },
            {
              "type" : "ResourceReport",
              "path" : "crates\/data\/src\/Gumbo_Structs_Arrays\/MyStruct2_i.rs",
              "overwrittenIfExists" : true
            },
            {
              "type" : "ResourceReport",
              "path" : "crates\/data\/src\/Gumbo_Structs_Arrays\/MyArrayInt32.rs",
              "overwrittenIfExists" : true
            },
            {
              "type" : "ResourceReport",
              "path" : "crates\/data\/src\/Gumbo_Structs_Arrays\/MyArrayStruct.rs",
              "overwrittenIfExists" : true
            },
            {
              "type" : "ResourceReport",
              "path" : "crates\/data\/src\/Gumbo_Structs_Arrays\/MyStructArray_i.rs",
              "overwrittenIfExists" : true
            },
            {
              "type" : "ResourceReport",
              "path" : "crates\/data\/src\/Gumbo_Structs_Arrays\/mod.rs",
              "overwrittenIfExists" : true
            },
            {
              "type" : "ResourceReport",
              "path" : "crates\/data\/src\/sb_event_counter.rs",
              "overwrittenIfExists" : true
            },
            {
              "type" : "ResourceReport",
              "path" : "crates\/data\/src\/sb_microkit_types.rs",
              "overwrittenIfExists" : true
            },
            {
              "type" : "ResourceReport",
              "path" : "crates\/data\/src\/lib.rs",
              "overwrittenIfExists" : true
            },
            {
              "type" : "ResourceReport",
              "path" : "crates\/data\/Cargo.toml",
              "overwrittenIfExists" : false
            },
            {
              "type" : "ResourceReport",
              "path" : "crates\/data\/rust-toolchain.toml",
              "overwrittenIfExists" : false
            },
            {
              "type" : "ResourceReport",
              "path" : "crates\/producer_producer\/src\/bridge\/extern_c_api.rs",
              "overwrittenIfExists" : true
            },
            {
              "type" : "ResourceReport",
              "path" : "crates\/producer_producer\/src\/bridge\/producer_producer_api.rs",
              "overwrittenIfExists" : true
            },
            {
              "type" : "ResourceReport",
              "path" : "crates\/producer_producer\/src\/bridge\/mod.rs",
              "overwrittenIfExists" : true
            },
            {
              "type" : "ResourceReport",
              "path" : "crates\/consumer_consumer\/src\/bridge\/extern_c_api.rs",
              "overwrittenIfExists" : true
            },
            {
              "type" : "ResourceReport",
              "path" : "crates\/consumer_consumer\/src\/bridge\/consumer_consumer_api.rs",
              "overwrittenIfExists" : true
            },
            {
              "type" : "ResourceReport",
              "path" : "crates\/consumer_consumer\/src\/bridge\/mod.rs",
              "overwrittenIfExists" : true
            },
            {
              "type" : "ResourceReport",
              "path" : "crates\/producer_producer\/src\/lib.rs",
              "overwrittenIfExists" : true
            },
            {
              "type" : "ResourceReport",
              "path" : "crates\/producer_producer\/src\/logging.rs",
              "overwrittenIfExists" : false
            },
            {
              "type" : "ResourceReport",
              "path" : "crates\/producer_producer\/src\/component\/producer_producer_app.rs",
              "overwrittenIfExists" : false
            },
            {
              "type" : "ResourceReport",
              "path" : "crates\/producer_producer\/src\/component\/mod.rs",
              "overwrittenIfExists" : false
            },
            {
              "type" : "ResourceReport",
              "path" : "crates\/producer_producer\/Cargo.toml",
              "overwrittenIfExists" : false
            },
            {
              "type" : "ResourceReport",
              "path" : "crates\/producer_producer\/Makefile",
              "overwrittenIfExists" : false
            },
            {
              "type" : "ResourceReport",
              "path" : "crates\/producer_producer\/rust-toolchain.toml",
              "overwrittenIfExists" : false
            },
            {
              "type" : "ResourceReport",
              "path" : "crates\/consumer_consumer\/src\/lib.rs",
              "overwrittenIfExists" : true
            },
            {
              "type" : "ResourceReport",
              "path" : "crates\/consumer_consumer\/src\/logging.rs",
              "overwrittenIfExists" : false
            },
            {
              "type" : "ResourceReport",
              "path" : "crates\/consumer_consumer\/src\/component\/consumer_consumer_app.rs",
              "overwrittenIfExists" : false
            },
            {
              "type" : "ResourceReport",
              "path" : "crates\/consumer_consumer\/src\/component\/mod.rs",
              "overwrittenIfExists" : false
            },
            {
              "type" : "ResourceReport",
              "path" : "crates\/consumer_consumer\/Cargo.toml",
              "overwrittenIfExists" : false
            },
            {
              "type" : "ResourceReport",
              "path" : "crates\/consumer_consumer\/Makefile",
              "overwrittenIfExists" : false
            },
            {
              "type" : "ResourceReport",
              "path" : "crates\/consumer_consumer\/rust-toolchain.toml",
              "overwrittenIfExists" : false
            },
            {
              "type" : "ResourceReport",
              "path" : "crates\/producer_producer\/src\/test\/mod.rs",
              "overwrittenIfExists" : false
            },
            {
              "type" : "ResourceReport",
              "path" : "crates\/producer_producer\/src\/test\/tests.rs",
              "overwrittenIfExists" : false
            },
            {
              "type" : "ResourceReport",
              "path" : "crates\/producer_producer\/src\/test\/util\/mod.rs",
              "overwrittenIfExists" : true
            },
            {
              "type" : "ResourceReport",
              "path" : "crates\/producer_producer\/src\/test\/util\/generators.rs",
              "overwrittenIfExists" : true
            },
            {
              "type" : "ResourceReport",
              "path" : "crates\/producer_producer\/src\/test\/util\/test_apis.rs",
              "overwrittenIfExists" : true
            },
            {
              "type" : "ResourceReport",
              "path" : "crates\/consumer_consumer\/src\/test\/mod.rs",
              "overwrittenIfExists" : false
            },
            {
              "type" : "ResourceReport",
              "path" : "crates\/consumer_consumer\/src\/test\/tests.rs",
              "overwrittenIfExists" : false
            },
            {
              "type" : "ResourceReport",
              "path" : "crates\/consumer_consumer\/src\/test\/util\/mod.rs",
              "overwrittenIfExists" : true
            },
            {
              "type" : "ResourceReport",
              "path" : "crates\/consumer_consumer\/src\/test\/util\/generators.rs",
              "overwrittenIfExists" : true
            },
            {
              "type" : "ResourceReport",
              "path" : "crates\/consumer_consumer\/src\/test\/util\/test_apis.rs",
              "overwrittenIfExists" : true
            },
            {
              "type" : "ResourceReport",
              "path" : "crates\/consumer_consumer\/src\/bridge\/consumer_consumer_GUMBOX.rs",
              "overwrittenIfExists" : true
            },
            {
              "type" : "ResourceReport",
              "path" : "crates\/consumer_consumer\/src\/test\/util\/cb_apis.rs",
              "overwrittenIfExists" : true
            }
          ]
        }
      ],
      [
        "MicrokitReporterPlugin",
        {
          "type" : "org.sireum.hamr.codegen.microkit.reporting.MicrokitReport",
          "componentReport" : {
            "type" : "HashSMap",
            "size" : 2,
            "entries" : [
              [
                {
                  "type" : "org.sireum.hamr.codegen.microkit.reporting.IdPathR",
                  "idPath" : ["Sys_i_Instance", "producer", "producer"]
                },
                {
                  "type" : "org.sireum.hamr.codegen.microkit.reporting.ComponentReport",
                  "path" : ["Sys_i_Instance", "producer", "producer"],
                  "kind" : {
                    "type" : "org.sireum.hamr.codegen.microkit.reporting.ComponentKind",
                    "value" : "Thread"
                  },
                  "optModelType" : {
                    "type" : "None"
                  },
                  "modelImplementation" : {
                    "type" : "org.sireum.hamr.codegen.microkit.reporting.IdPos",
                    "id" : "Gumbo_Structs_Arrays::ProducerThr.i",
                    "pos" : {
                      "type" : "Position",
                      "uriOpt" : {
                        "type" : "Some",
                        "value" : "\/microkit-gumbo-verus-structs-arrays\/Gumbo_Structs_Arrays.aadl"
                      },
                      "beginLine" : 125,
                      "beginColumn" : 7,
                      "endLine" : 125,
                      "endColumn" : 38,
                      "offset" : 3830,
                      "length" : 31
                    }
                  },
                  "modelProperties" : [
                  ],
                  "subcomponents" : [
                  ],
                  "ports" : {
                    "type" : "HashSMap",
                    "size" : 2,
                    "entries" : [
                      [
                        {
                          "type" : "org.sireum.hamr.codegen.microkit.reporting.IdPathR",
                          "idPath" : ["Sys_i_Instance", "producer", "producer", "myStructArray"]
                        },
                        {
                          "type" : "org.sireum.hamr.codegen.microkit.reporting.PortReport",
                          "name" : ["Sys_i_Instance", "producer", "producer", "myStructArray"],
                          "kind" : {
                            "type" : "org.sireum.hamr.codegen.microkit.reporting.PortKind",
                            "value" : "EventData"
                          },
                          "direction" : {
                            "type" : "org.sireum.hamr.codegen.microkit.reporting.PortDirection",
                            "value" : "Out"
                          },
                          "payload" : {
                            "type" : "Some",
                            "value" : "Gumbo_Structs_Arrays::MyStructArray.i"
                          },
                          "modelPos" : {
                            "type" : "Position",
                            "uriOpt" : {
                              "type" : "Some",
                              "value" : "..\/..\/aadl\/Gumbo_Structs_Arrays.aadl"
                            },
                            "beginLine" : 160,
                            "beginColumn" : 7,
                            "endLine" : 160,
                            "endColumn" : 58,
                            "offset" : 4961,
                            "length" : 51
                          },
                          "languageRealizations" : [
                            {
                              "type" : "org.sireum.hamr.codegen.microkit.reporting.PortLanguageArtifact",
                              "name" : "Rust\/Verus API",
                              "title" : "Rust\/Verus API",
                              "pos" : {
                                "type" : "Position",
                                "uriOpt" : {
                                  "type" : "Some",
                                  "value" : "crates\/producer_producer\/src\/bridge\/producer_producer_api.rs"
                                },
                                "beginLine" : 41,
                                "beginColumn" : 9,
                                "endLine" : 50,
                                "endColumn" : 5,
                                "offset" : 1167,
                                "length" : 305
                              }
                            },
                            {
                              "type" : "org.sireum.hamr.codegen.microkit.reporting.PortLanguageArtifact",
                              "name" : "Unverified Rust Interface",
                              "title" : "Unverified Rust Interface",
                              "pos" : {
                                "type" : "Position",
                                "uriOpt" : {
                                  "type" : "Some",
                                  "value" : "crates\/producer_producer\/src\/bridge\/producer_producer_api.rs"
                                },
                                "beginLine" : 12,
                                "beginColumn" : 5,
                                "endLine" : 17,
                                "endColumn" : 5,
                                "offset" : 292,
                                "length" : 164
                              }
                            },
                            {
                              "type" : "org.sireum.hamr.codegen.microkit.reporting.PortLanguageArtifact",
                              "name" : "Rust\/C Interface",
                              "title" : "Rust\/C Interface",
                              "pos" : {
                                "type" : "Position",
                                "uriOpt" : {
                                  "type" : "Some",
                                  "value" : "crates\/producer_producer\/src\/bridge\/extern_c_api.rs"
                                },
                                "beginLine" : 18,
                                "beginColumn" : 5,
                                "endLine" : 23,
                                "endColumn" : 1,
                                "offset" : 479,
                                "length" : 231
                              }
                            },
                            {
                              "type" : "org.sireum.hamr.codegen.microkit.reporting.PortLanguageArtifact",
                              "name" : "C Extern",
                              "title" : "C Extern",
                              "pos" : {
                                "type" : "Position",
                                "uriOpt" : {
                                  "type" : "Some",
                                  "value" : "crates\/producer_producer\/src\/bridge\/extern_c_api.rs"
                                },
                                "beginLine" : 14,
                                "beginColumn" : 3,
                                "endLine" : 14,
                                "endColumn" : 82,
                                "offset" : 310,
                                "length" : 79
                              }
                            },
                            {
                              "type" : "org.sireum.hamr.codegen.microkit.reporting.PortLanguageArtifact",
                              "name" : "C Interface",
                              "title" : "C Interface",
                              "pos" : {
                                "type" : "Position",
                                "uriOpt" : {
                                  "type" : "Some",
                                  "value" : "components\/producer_producer\/src\/producer_producer.c"
                                },
                                "beginLine" : 14,
                                "beginColumn" : 1,
                                "endLine" : 18,
                                "endColumn" : 1,
                                "offset" : 438,
                                "length" : 274
                              }
                            },
                            {
                              "type" : "org.sireum.hamr.codegen.microkit.reporting.PortLanguageArtifact",
                              "name" : "C var_addr",
                              "title" : "C Shared Memory Variable",
                              "pos" : {
                                "type" : "Position",
                                "uriOpt" : {
                                  "type" : "Some",
                                  "value" : "components\/producer_producer\/src\/producer_producer.c"
                                },
                                "beginLine" : 9,
                                "beginColumn" : 1,
                                "endLine" : 9,
                                "endColumn" : 82,
                                "offset" : 247,
                                "length" : 81
                              }
                            },
                            {
                              "type" : "org.sireum.hamr.codegen.microkit.reporting.PortLanguageArtifact",
                              "name" : "Memory Map",
                              "title" : "Memory Map",
                              "pos" : {
                                "type" : "Position",
                                "uriOpt" : {
                                  "type" : "Some",
                                  "value" : "microkit.system"
                                },
                                "beginLine" : 11,
                                "beginColumn" : 7,
                                "endLine" : 15,
                                "endColumn" : 9,
                                "offset" : 0,
                                "length" : 0
                              }
                            }
                          ]
                        }
                      ],
                      [
                        {
                          "type" : "org.sireum.hamr.codegen.microkit.reporting.IdPathR",
                          "idPath" : ["Sys_i_Instance", "producer", "producer", "MyArrayStruct"]
                        },
                        {
                          "type" : "org.sireum.hamr.codegen.microkit.reporting.PortReport",
                          "name" : ["Sys_i_Instance", "producer", "producer", "MyArrayStruct"],
                          "kind" : {
                            "type" : "org.sireum.hamr.codegen.microkit.reporting.PortKind",
                            "value" : "EventData"
                          },
                          "direction" : {
                            "type" : "org.sireum.hamr.codegen.microkit.reporting.PortDirection",
                            "value" : "Out"
                          },
                          "payload" : {
                            "type" : "Some",
                            "value" : "Gumbo_Structs_Arrays::MyArrayStruct"
                          },
                          "modelPos" : {
                            "type" : "Position",
                            "uriOpt" : {
                              "type" : "Some",
                              "value" : "..\/..\/aadl\/Gumbo_Structs_Arrays.aadl"
                            },
                            "beginLine" : 161,
                            "beginColumn" : 7,
                            "endLine" : 161,
                            "endColumn" : 57,
                            "offset" : 5019,
                            "length" : 50
                          },
                          "languageRealizations" : [
                            {
                              "type" : "org.sireum.hamr.codegen.microkit.reporting.PortLanguageArtifact",
                              "name" : "Rust\/Verus API",
                              "title" : "Rust\/Verus API",
                              "pos" : {
                                "type" : "Position",
                                "uriOpt" : {
                                  "type" : "Some",
                                  "value" : "crates\/producer_producer\/src\/bridge\/producer_producer_api.rs"
                                },
                                "beginLine" : 51,
                                "beginColumn" : 9,
                                "endLine" : 60,
                                "endColumn" : 5,
                                "offset" : 1482,
                                "length" : 303
                              }
                            },
                            {
                              "type" : "org.sireum.hamr.codegen.microkit.reporting.PortLanguageArtifact",
                              "name" : "Unverified Rust Interface",
                              "title" : "Unverified Rust Interface",
                              "pos" : {
                                "type" : "Position",
                                "uriOpt" : {
                                  "type" : "Some",
                                  "value" : "crates\/producer_producer\/src\/bridge\/producer_producer_api.rs"
                                },
                                "beginLine" : 20,
                                "beginColumn" : 5,
                                "endLine" : 25,
                                "endColumn" : 5,
                                "offset" : 494,
                                "length" : 162
                              }
                            },
                            {
                              "type" : "org.sireum.hamr.codegen.microkit.reporting.PortLanguageArtifact",
                              "name" : "Rust\/C Interface",
                              "title" : "Rust\/C Interface",
                              "pos" : {
                                "type" : "Position",
                                "uriOpt" : {
                                  "type" : "Some",
                                  "value" : "crates\/producer_producer\/src\/bridge\/extern_c_api.rs"
                                },
                                "beginLine" : 25,
                                "beginColumn" : 5,
                                "endLine" : 30,
                                "endColumn" : 1,
                                "offset" : 717,
                                "length" : 225
                              }
                            },
                            {
                              "type" : "org.sireum.hamr.codegen.microkit.reporting.PortLanguageArtifact",
                              "name" : "C Extern",
                              "title" : "C Extern",
                              "pos" : {
                                "type" : "Position",
                                "uriOpt" : {
                                  "type" : "Some",
                                  "value" : "crates\/producer_producer\/src\/bridge\/extern_c_api.rs"
                                },
                                "beginLine" : 15,
                                "beginColumn" : 3,
                                "endLine" : 15,
                                "endColumn" : 80,
                                "offset" : 393,
                                "length" : 77
                              }
                            },
                            {
                              "type" : "org.sireum.hamr.codegen.microkit.reporting.PortLanguageArtifact",
                              "name" : "C Interface",
                              "title" : "C Interface",
                              "pos" : {
                                "type" : "Position",
                                "uriOpt" : {
                                  "type" : "Some",
                                  "value" : "components\/producer_producer\/src\/producer_producer.c"
                                },
                                "beginLine" : 20,
                                "beginColumn" : 1,
                                "endLine" : 24,
                                "endColumn" : 1,
                                "offset" : 715,
                                "length" : 266
                              }
                            },
                            {
                              "type" : "org.sireum.hamr.codegen.microkit.reporting.PortLanguageArtifact",
                              "name" : "C var_addr",
                              "title" : "C Shared Memory Variable",
                              "pos" : {
                                "type" : "Position",
                                "uriOpt" : {
                                  "type" : "Some",
                                  "value" : "components\/producer_producer\/src\/producer_producer.c"
                                },
                                "beginLine" : 10,
                                "beginColumn" : 1,
                                "endLine" : 10,
                                "endColumn" : 80,
                                "offset" : 330,
                                "length" : 79
                              }
                            },
                            {
                              "type" : "org.sireum.hamr.codegen.microkit.reporting.PortLanguageArtifact",
                              "name" : "Memory Map",
                              "title" : "Memory Map",
                              "pos" : {
                                "type" : "Position",
                                "uriOpt" : {
                                  "type" : "Some",
                                  "value" : "microkit.system"
                                },
                                "beginLine" : 16,
                                "beginColumn" : 7,
                                "endLine" : 20,
                                "endColumn" : 9,
                                "offset" : 0,
                                "length" : 0
                              }
                            }
                          ]
                        }
                      ]
                    ]
                  },
                  "cCodeReport" : {
                    "type" : "None"
                  },
                  "rustReport" : {
                    "type" : "Some",
                    "value" : {
                      "type" : "org.sireum.hamr.codegen.microkit.reporting.RustReport",
                      "entrypointReport" : {
                        "type" : "HashSMap",
                        "size" : 2,
                        "entries" : [
                          [
                            "initialize",
                            {
                              "type" : "Position",
                              "uriOpt" : {
                                "type" : "Some",
                                "value" : "crates\/producer_producer\/src\/component\/producer_producer_app.rs"
                              },
                              "beginLine" : 16,
                              "beginColumn" : 7,
                              "endLine" : 21,
                              "endColumn" : 3,
                              "offset" : 231,
                              "length" : 170
                            }
                          ],
                          [
                            "timeTriggered",
                            {
                              "type" : "Position",
                              "uriOpt" : {
                                "type" : "Some",
                                "value" : "crates\/producer_producer\/src\/component\/producer_producer_app.rs"
                              },
                              "beginLine" : 23,
                              "beginColumn" : 7,
                              "endLine" : 28,
                              "endColumn" : 3,
                              "offset" : 410,
                              "length" : 171
                            }
                          ]
                        ]
                      },
                      "apiReport" : {
                        "type" : "org.sireum.hamr.codegen.microkit.reporting.RustApiReport",
                        "extern_c_apiPath" : "crates\/producer_producer\/src\/bridge\/extern_c_api.rs",
                        "developerApiPath" : "crates\/producer_producer\/src\/bridge\/producer_producer_api.rs",
                        "developerApiReport" : {
                          "type" : "HashSMap",
                          "size" : 0,
                          "entries" : [
                          ]
                        },
                        "testApiPath" : "crates\/producer_producer\/src\/test\/util\/test_apis.rs"
                      }
                    }
                  },
                  "gumboReport" : {
                    "type" : "None"
                  },
                  "gumboXReport" : {
                    "type" : "None"
                  }
                }
              ],
              [
                {
                  "type" : "org.sireum.hamr.codegen.microkit.reporting.IdPathR",
                  "idPath" : ["Sys_i_Instance", "consumer", "consumer"]
                },
                {
                  "type" : "org.sireum.hamr.codegen.microkit.reporting.ComponentReport",
                  "path" : ["Sys_i_Instance", "consumer", "consumer"],
                  "kind" : {
                    "type" : "org.sireum.hamr.codegen.microkit.reporting.ComponentKind",
                    "value" : "Thread"
                  },
                  "optModelType" : {
                    "type" : "None"
                  },
                  "modelImplementation" : {
                    "type" : "org.sireum.hamr.codegen.microkit.reporting.IdPos",
                    "id" : "Gumbo_Structs_Arrays::ConsumerThr.i",
                    "pos" : {
                      "type" : "Position",
                      "uriOpt" : {
                        "type" : "Some",
                        "value" : "\/microkit-gumbo-verus-structs-arrays\/Gumbo_Structs_Arrays.aadl"
                      },
                      "beginLine" : 143,
                      "beginColumn" : 7,
                      "endLine" : 143,
                      "endColumn" : 38,
                      "offset" : 4364,
                      "length" : 31
                    }
                  },
                  "modelProperties" : [
                  ],
                  "subcomponents" : [
                  ],
                  "ports" : {
                    "type" : "HashSMap",
                    "size" : 3,
                    "entries" : [
                      [
                        {
                          "type" : "org.sireum.hamr.codegen.microkit.reporting.IdPathR",
                          "idPath" : ["Sys_i_Instance", "consumer", "consumer", "myStructArray"]
                        },
                        {
                          "type" : "org.sireum.hamr.codegen.microkit.reporting.PortReport",
                          "name" : ["Sys_i_Instance", "consumer", "consumer", "myStructArray"],
                          "kind" : {
                            "type" : "org.sireum.hamr.codegen.microkit.reporting.PortKind",
                            "value" : "EventData"
                          },
                          "direction" : {
                            "type" : "org.sireum.hamr.codegen.microkit.reporting.PortDirection",
                            "value" : "In"
                          },
                          "payload" : {
                            "type" : "Some",
                            "value" : "Gumbo_Structs_Arrays::MyStructArray.i"
                          },
                          "modelPos" : {
                            "type" : "Position",
                            "uriOpt" : {
                              "type" : "Some",
                              "value" : "..\/..\/aadl\/Gumbo_Structs_Arrays.aadl"
                            },
                            "beginLine" : 172,
                            "beginColumn" : 7,
                            "endLine" : 172,
                            "endColumn" : 57,
                            "offset" : 5266,
                            "length" : 50
                          },
                          "languageRealizations" : [
                            {
                              "type" : "org.sireum.hamr.codegen.microkit.reporting.PortLanguageArtifact",
                              "name" : "Rust\/Verus API",
                              "title" : "Rust\/Verus API",
                              "pos" : {
                                "type" : "Position",
                                "uriOpt" : {
                                  "type" : "Some",
                                  "value" : "crates\/consumer_consumer\/src\/bridge\/consumer_consumer_api.rs"
                                },
                                "beginLine" : 59,
                                "beginColumn" : 9,
                                "endLine" : 67,
                                "endColumn" : 5,
                                "offset" : 1849,
                                "length" : 383
                              }
                            },
                            {
                              "type" : "org.sireum.hamr.codegen.microkit.reporting.PortLanguageArtifact",
                              "name" : "Unverified Rust Interface",
                              "title" : "Unverified Rust Interface",
                              "pos" : {
                                "type" : "Position",
                                "uriOpt" : {
                                  "type" : "Some",
                                  "value" : "crates\/consumer_consumer\/src\/bridge\/consumer_consumer_api.rs"
                                },
                                "beginLine" : 15,
                                "beginColumn" : 5,
                                "endLine" : 22,
                                "endColumn" : 5,
                                "offset" : 360,
                                "length" : 275
                              }
                            },
                            {
                              "type" : "org.sireum.hamr.codegen.microkit.reporting.PortLanguageArtifact",
                              "name" : "Rust\/C Interface",
                              "title" : "Rust\/C Interface",
                              "pos" : {
                                "type" : "Position",
                                "uriOpt" : {
                                  "type" : "Some",
                                  "value" : "crates\/consumer_consumer\/src\/bridge\/extern_c_api.rs"
                                },
                                "beginLine" : 19,
                                "beginColumn" : 5,
                                "endLine" : 29,
                                "endColumn" : 1,
                                "offset" : 558,
                                "length" : 312
                              }
                            },
                            {
                              "type" : "org.sireum.hamr.codegen.microkit.reporting.PortLanguageArtifact",
                              "name" : "C Extern",
                              "title" : "C Extern",
                              "pos" : {
                                "type" : "Position",
                                "uriOpt" : {
                                  "type" : "Some",
                                  "value" : "crates\/consumer_consumer\/src\/bridge\/extern_c_api.rs"
                                },
                                "beginLine" : 14,
                                "beginColumn" : 3,
                                "endLine" : 14,
                                "endColumn" : 82,
                                "offset" : 310,
                                "length" : 79
                              }
                            },
                            {
                              "type" : "org.sireum.hamr.codegen.microkit.reporting.PortLanguageArtifact",
                              "name" : "C Interface",
                              "title" : "C Interface",
                              "pos" : {
                                "type" : "Position",
                                "uriOpt" : {
                                  "type" : "Some",
                                  "value" : "components\/consumer_consumer\/src\/consumer_consumer.c"
                                },
                                "beginLine" : 26,
                                "beginColumn" : 1,
                                "endLine" : 29,
                                "endColumn" : 1,
                                "offset" : 1166,
                                "length" : 155
                              }
                            },
                            {
                              "type" : "org.sireum.hamr.codegen.microkit.reporting.PortLanguageArtifact",
                              "name" : "C var_addr",
                              "title" : "C Shared Memory Variable",
                              "pos" : {
                                "type" : "Position",
                                "uriOpt" : {
                                  "type" : "Some",
                                  "value" : "components\/consumer_consumer\/src\/consumer_consumer.c"
                                },
                                "beginLine" : 9,
                                "beginColumn" : 1,
                                "endLine" : 9,
                                "endColumn" : 82,
                                "offset" : 247,
                                "length" : 81
                              }
                            },
                            {
                              "type" : "org.sireum.hamr.codegen.microkit.reporting.PortLanguageArtifact",
                              "name" : "Memory Map",
                              "title" : "Memory Map",
                              "pos" : {
                                "type" : "Position",
                                "uriOpt" : {
                                  "type" : "Some",
                                  "value" : "microkit.system"
                                },
                                "beginLine" : 34,
                                "beginColumn" : 7,
                                "endLine" : 38,
                                "endColumn" : 9,
                                "offset" : 0,
                                "length" : 0
                              }
                            }
                          ]
                        }
                      ],
                      [
                        {
                          "type" : "org.sireum.hamr.codegen.microkit.reporting.IdPathR",
                          "idPath" : ["Sys_i_Instance", "consumer", "consumer", "MyArrayStruct"]
                        },
                        {
                          "type" : "org.sireum.hamr.codegen.microkit.reporting.PortReport",
                          "name" : ["Sys_i_Instance", "consumer", "consumer", "MyArrayStruct"],
                          "kind" : {
                            "type" : "org.sireum.hamr.codegen.microkit.reporting.PortKind",
                            "value" : "EventData"
                          },
                          "direction" : {
                            "type" : "org.sireum.hamr.codegen.microkit.reporting.PortDirection",
                            "value" : "In"
                          },
                          "payload" : {
                            "type" : "Some",
                            "value" : "Gumbo_Structs_Arrays::MyArrayStruct"
                          },
                          "modelPos" : {
                            "type" : "Position",
                            "uriOpt" : {
                              "type" : "Some",
                              "value" : "..\/..\/aadl\/Gumbo_Structs_Arrays.aadl"
                            },
                            "beginLine" : 173,
                            "beginColumn" : 7,
                            "endLine" : 173,
                            "endColumn" : 56,
                            "offset" : 5323,
                            "length" : 49
                          },
                          "languageRealizations" : [
                            {
                              "type" : "org.sireum.hamr.codegen.microkit.reporting.PortLanguageArtifact",
                              "name" : "Rust\/Verus API",
                              "title" : "Rust\/Verus API",
                              "pos" : {
                                "type" : "Position",
                                "uriOpt" : {
                                  "type" : "Some",
                                  "value" : "crates\/consumer_consumer\/src\/bridge\/consumer_consumer_api.rs"
                                },
                                "beginLine" : 68,
                                "beginColumn" : 9,
                                "endLine" : 76,
                                "endColumn" : 5,
                                "offset" : 2242,
                                "length" : 381
                              }
                            },
                            {
                              "type" : "org.sireum.hamr.codegen.microkit.reporting.PortLanguageArtifact",
                              "name" : "Unverified Rust Interface",
                              "title" : "Unverified Rust Interface",
                              "pos" : {
                                "type" : "Position",
                                "uriOpt" : {
                                  "type" : "Some",
                                  "value" : "crates\/consumer_consumer\/src\/bridge\/consumer_consumer_api.rs"
                                },
                                "beginLine" : 25,
                                "beginColumn" : 5,
                                "endLine" : 32,
                                "endColumn" : 5,
                                "offset" : 673,
                                "length" : 271
                              }
                            },
                            {
                              "type" : "org.sireum.hamr.codegen.microkit.reporting.PortLanguageArtifact",
                              "name" : "Rust\/C Interface",
                              "title" : "Rust\/C Interface",
                              "pos" : {
                                "type" : "Position",
                                "uriOpt" : {
                                  "type" : "Some",
                                  "value" : "crates\/consumer_consumer\/src\/bridge\/extern_c_api.rs"
                                },
                                "beginLine" : 31,
                                "beginColumn" : 5,
                                "endLine" : 41,
                                "endColumn" : 1,
                                "offset" : 877,
                                "length" : 370
                              }
                            },
                            {
                              "type" : "org.sireum.hamr.codegen.microkit.reporting.PortLanguageArtifact",
                              "name" : "C Extern",
                              "title" : "C Extern",
                              "pos" : {
                                "type" : "Position",
                                "uriOpt" : {
                                  "type" : "Some",
                                  "value" : "crates\/consumer_consumer\/src\/bridge\/extern_c_api.rs"
                                },
                                "beginLine" : 15,
                                "beginColumn" : 3,
                                "endLine" : 15,
                                "endColumn" : 80,
                                "offset" : 393,
                                "length" : 77
                              }
                            },
                            {
                              "type" : "org.sireum.hamr.codegen.microkit.reporting.PortLanguageArtifact",
                              "name" : "C Interface",
                              "title" : "C Interface",
                              "pos" : {
                                "type" : "Position",
                                "uriOpt" : {
                                  "type" : "Some",
                                  "value" : "components\/consumer_consumer\/src\/consumer_consumer.c"
                                },
                                "beginLine" : 39,
                                "beginColumn" : 1,
                                "endLine" : 42,
                                "endColumn" : 1,
                                "offset" : 1728,
                                "length" : 153
                              }
                            },
                            {
                              "type" : "org.sireum.hamr.codegen.microkit.reporting.PortLanguageArtifact",
                              "name" : "C var_addr",
                              "title" : "C Shared Memory Variable",
                              "pos" : {
                                "type" : "Position",
                                "uriOpt" : {
                                  "type" : "Some",
                                  "value" : "components\/consumer_consumer\/src\/consumer_consumer.c"
                                },
                                "beginLine" : 11,
                                "beginColumn" : 1,
                                "endLine" : 11,
                                "endColumn" : 80,
                                "offset" : 411,
                                "length" : 79
                              }
                            },
                            {
                              "type" : "org.sireum.hamr.codegen.microkit.reporting.PortLanguageArtifact",
                              "name" : "Memory Map",
                              "title" : "Memory Map",
                              "pos" : {
                                "type" : "Position",
                                "uriOpt" : {
                                  "type" : "Some",
                                  "value" : "microkit.system"
                                },
                                "beginLine" : 39,
                                "beginColumn" : 7,
                                "endLine" : 43,
                                "endColumn" : 9,
                                "offset" : 0,
                                "length" : 0
                              }
                            }
                          ]
                        }
                      ],
                      [
                        {
                          "type" : "org.sireum.hamr.codegen.microkit.reporting.IdPathR",
                          "idPath" : ["Sys_i_Instance", "consumer", "consumer", "MyArrayInt32"]
                        },
                        {
                          "type" : "org.sireum.hamr.codegen.microkit.reporting.PortReport",
                          "name" : ["Sys_i_Instance", "consumer", "consumer", "MyArrayInt32"],
                          "kind" : {
                            "type" : "org.sireum.hamr.codegen.microkit.reporting.PortKind",
                            "value" : "EventData"
                          },
                          "direction" : {
                            "type" : "org.sireum.hamr.codegen.microkit.reporting.PortDirection",
                            "value" : "In"
                          },
                          "payload" : {
                            "type" : "Some",
                            "value" : "Gumbo_Structs_Arrays::MyArrayInt32"
                          },
                          "modelPos" : {
                            "type" : "Position",
                            "uriOpt" : {
                              "type" : "Some",
                              "value" : "..\/..\/aadl\/Gumbo_Structs_Arrays.aadl"
                            },
                            "beginLine" : 174,
                            "beginColumn" : 7,
                            "endLine" : 174,
                            "endColumn" : 53,
                            "offset" : 5379,
                            "length" : 46
                          },
                          "languageRealizations" : [
                            {
                              "type" : "org.sireum.hamr.codegen.microkit.reporting.PortLanguageArtifact",
                              "name" : "Rust\/Verus API",
                              "title" : "Rust\/Verus API",
                              "pos" : {
                                "type" : "Position",
                                "uriOpt" : {
                                  "type" : "Some",
                                  "value" : "crates\/consumer_consumer\/src\/bridge\/consumer_consumer_api.rs"
                                },
                                "beginLine" : 77,
                                "beginColumn" : 9,
                                "endLine" : 85,
                                "endColumn" : 5,
                                "offset" : 2633,
                                "length" : 376
                              }
                            },
                            {
                              "type" : "org.sireum.hamr.codegen.microkit.reporting.PortLanguageArtifact",
                              "name" : "Unverified Rust Interface",
                              "title" : "Unverified Rust Interface",
                              "pos" : {
                                "type" : "Position",
                                "uriOpt" : {
                                  "type" : "Some",
                                  "value" : "crates\/consumer_consumer\/src\/bridge\/consumer_consumer_api.rs"
                                },
                                "beginLine" : 35,
                                "beginColumn" : 5,
                                "endLine" : 42,
                                "endColumn" : 5,
                                "offset" : 982,
                                "length" : 267
                              }
                            },
                            {
                              "type" : "org.sireum.hamr.codegen.microkit.reporting.PortLanguageArtifact",
                              "name" : "Rust\/C Interface",
                              "title" : "Rust\/C Interface",
                              "pos" : {
                                "type" : "Position",
                                "uriOpt" : {
                                  "type" : "Some",
                                  "value" : "crates\/consumer_consumer\/src\/bridge\/extern_c_api.rs"
                                },
                                "beginLine" : 43,
                                "beginColumn" : 5,
                                "endLine" : 53,
                                "endColumn" : 1,
                                "offset" : 1254,
                                "length" : 322
                              }
                            },
                            {
                              "type" : "org.sireum.hamr.codegen.microkit.reporting.PortLanguageArtifact",
                              "name" : "C Extern",
                              "title" : "C Extern",
                              "pos" : {
                                "type" : "Position",
                                "uriOpt" : {
                                  "type" : "Some",
                                  "value" : "crates\/consumer_consumer\/src\/bridge\/extern_c_api.rs"
                                },
                                "beginLine" : 16,
                                "beginColumn" : 3,
                                "endLine" : 16,
                                "endColumn" : 78,
                                "offset" : 474,
                                "length" : 75
                              }
                            },
                            {
                              "type" : "org.sireum.hamr.codegen.microkit.reporting.PortLanguageArtifact",
                              "name" : "C Interface",
                              "title" : "C Interface",
                              "pos" : {
                                "type" : "Position",
                                "uriOpt" : {
                                  "type" : "Some",
                                  "value" : "components\/consumer_consumer\/src\/consumer_consumer.c"
                                },
                                "beginLine" : 52,
                                "beginColumn" : 1,
                                "endLine" : 55,
                                "endColumn" : 1,
                                "offset" : 2280,
                                "length" : 150
                              }
                            },
                            {
                              "type" : "org.sireum.hamr.codegen.microkit.reporting.PortLanguageArtifact",
                              "name" : "C var_addr",
                              "title" : "C Shared Memory Variable",
                              "pos" : {
                                "type" : "Position",
                                "uriOpt" : {
                                  "type" : "Some",
                                  "value" : "components\/consumer_consumer\/src\/consumer_consumer.c"
                                },
                                "beginLine" : 13,
                                "beginColumn" : 1,
                                "endLine" : 13,
                                "endColumn" : 78,
                                "offset" : 571,
                                "length" : 77
                              }
                            },
                            {
                              "type" : "org.sireum.hamr.codegen.microkit.reporting.PortLanguageArtifact",
                              "name" : "Memory Map",
                              "title" : "Memory Map",
                              "pos" : {
                                "type" : "Position",
                                "uriOpt" : {
                                  "type" : "Some",
                                  "value" : "microkit.system"
                                },
                                "beginLine" : 44,
                                "beginColumn" : 7,
                                "endLine" : 48,
                                "endColumn" : 9,
                                "offset" : 0,
                                "length" : 0
                              }
                            }
                          ]
                        }
                      ]
                    ]
                  },
                  "cCodeReport" : {
                    "type" : "None"
                  },
                  "rustReport" : {
                    "type" : "Some",
                    "value" : {
                      "type" : "org.sireum.hamr.codegen.microkit.reporting.RustReport",
                      "entrypointReport" : {
                        "type" : "HashSMap",
                        "size" : 2,
                        "entries" : [
                          [
                            "initialize",
                            {
                              "type" : "Position",
                              "uriOpt" : {
                                "type" : "Some",
                                "value" : "crates\/consumer_consumer\/src\/component\/consumer_consumer_app.rs"
                              },
                              "beginLine" : 19,
                              "beginColumn" : 9,
                              "endLine" : 24,
                              "endColumn" : 5,
                              "offset" : 281,
                              "length" : 180
                            }
                          ],
                          [
                            "timeTriggered",
                            {
                              "type" : "Position",
                              "uriOpt" : {
                                "type" : "Some",
                                "value" : "crates\/consumer_consumer\/src\/component\/consumer_consumer_app.rs"
                              },
                              "beginLine" : 26,
                              "beginColumn" : 9,
                              "endLine" : 106,
                              "endColumn" : 5,
                              "offset" : 472,
                              "length" : 5019
                            }
                          ]
                        ]
                      },
                      "apiReport" : {
                        "type" : "org.sireum.hamr.codegen.microkit.reporting.RustApiReport",
                        "extern_c_apiPath" : "crates\/consumer_consumer\/src\/bridge\/extern_c_api.rs",
                        "developerApiPath" : "crates\/consumer_consumer\/src\/bridge\/consumer_consumer_api.rs",
                        "developerApiReport" : {
                          "type" : "HashSMap",
                          "size" : 0,
                          "entries" : [
                          ]
                        },
                        "testApiPath" : "crates\/consumer_consumer\/src\/test\/util\/test_apis.rs"
                      }
                    }
                  },
                  "gumboReport" : {
                    "type" : "Some",
                    "value" : {
                      "type" : "org.sireum.hamr.codegen.microkit.reporting.GumboReport",
                      "stateReport" : {
                        "type" : "HashSMap",
                        "size" : 0,
                        "entries" : [
                        ]
                      },
                      "methodsReport" : {
                        "type" : "HashSMap",
                        "size" : 9,
                        "entries" : [
                          [
                            "convertB",
                            {
                              "type" : "Position",
                              "uriOpt" : {
                                "type" : "Some",
                                "value" : "crates\/consumer_consumer\/src\/component\/consumer_consumer_app.rs"
                              },
                              "beginLine" : 134,
                              "beginColumn" : 17,
                              "endLine" : 144,
                              "endColumn" : 3,
                              "offset" : 6030,
                              "length" : 282
                            }
                          ],
                          [
                            "convertS8",
                            {
                              "type" : "Position",
                              "uriOpt" : {
                                "type" : "Some",
                                "value" : "crates\/consumer_consumer\/src\/component\/consumer_consumer_app.rs"
                              },
                              "beginLine" : 146,
                              "beginColumn" : 17,
                              "endLine" : 156,
                              "endColumn" : 3,
                              "offset" : 6331,
                              "length" : 281
                            }
                          ],
                          [
                            "convertS16",
                            {
                              "type" : "Position",
                              "uriOpt" : {
                                "type" : "Some",
                                "value" : "crates\/consumer_consumer\/src\/component\/consumer_consumer_app.rs"
                              },
                              "beginLine" : 158,
                              "beginColumn" : 17,
                              "endLine" : 168,
                              "endColumn" : 3,
                              "offset" : 6631,
                              "length" : 283
                            }
                          ],
                          [
                            "convertS32",
                            {
                              "type" : "Position",
                              "uriOpt" : {
                                "type" : "Some",
                                "value" : "crates\/consumer_consumer\/src\/component\/consumer_consumer_app.rs"
                              },
                              "beginLine" : 170,
                              "beginColumn" : 17,
                              "endLine" : 180,
                              "endColumn" : 3,
                              "offset" : 6933,
                              "length" : 283
                            }
                          ],
                          [
                            "convertS64",
                            {
                              "type" : "Position",
                              "uriOpt" : {
                                "type" : "Some",
                                "value" : "crates\/consumer_consumer\/src\/component\/consumer_consumer_app.rs"
                              },
                              "beginLine" : 182,
                              "beginColumn" : 17,
                              "endLine" : 192,
                              "endColumn" : 3,
                              "offset" : 7235,
                              "length" : 283
                            }
                          ],
                          [
                            "convertU8",
                            {
                              "type" : "Position",
                              "uriOpt" : {
                                "type" : "Some",
                                "value" : "crates\/consumer_consumer\/src\/component\/consumer_consumer_app.rs"
                              },
                              "beginLine" : 194,
                              "beginColumn" : 17,
                              "endLine" : 204,
                              "endColumn" : 3,
                              "offset" : 7537,
                              "length" : 281
                            }
                          ],
                          [
                            "convertU16",
                            {
                              "type" : "Position",
                              "uriOpt" : {
                                "type" : "Some",
                                "value" : "crates\/consumer_consumer\/src\/component\/consumer_consumer_app.rs"
                              },
                              "beginLine" : 206,
                              "beginColumn" : 17,
                              "endLine" : 216,
                              "endColumn" : 3,
                              "offset" : 7837,
                              "length" : 283
                            }
                          ],
                          [
                            "convertU32",
                            {
                              "type" : "Position",
                              "uriOpt" : {
                                "type" : "Some",
                                "value" : "crates\/consumer_consumer\/src\/component\/consumer_consumer_app.rs"
                              },
                              "beginLine" : 218,
                              "beginColumn" : 17,
                              "endLine" : 228,
                              "endColumn" : 3,
                              "offset" : 8139,
                              "length" : 283
                            }
                          ],
                          [
                            "convertU64",
                            {
                              "type" : "Position",
                              "uriOpt" : {
                                "type" : "Some",
                                "value" : "crates\/consumer_consumer\/src\/component\/consumer_consumer_app.rs"
                              },
                              "beginLine" : 230,
                              "beginColumn" : 17,
                              "endLine" : 240,
                              "endColumn" : 3,
                              "offset" : 8441,
                              "length" : 283
                            }
                          ]
                        ]
                      },
                      "invariantsReport" : {
                        "type" : "HashSMap",
                        "size" : 0,
                        "entries" : [
                        ]
                      },
                      "integrationReport" : {
                        "type" : "None"
                      },
                      "initializeReport" : {
                        "type" : "HashSMap",
                        "size" : 0,
                        "entries" : [
                        ]
                      },
                      "computeReport" : {
                        "type" : "Some",
                        "value" : {
                          "type" : "org.sireum.hamr.codegen.microkit.reporting.GumboComputeReport",
                          "assumesReport" : {
                            "type" : "HashSMap",
                            "size" : 6,
                            "entries" : [
                              [
                                "isSorted_StructArray",
                                {
                                  "type" : "Position",
                                  "uriOpt" : {
                                    "type" : "Some",
                                    "value" : "crates\/consumer_consumer\/src\/component\/consumer_consumer_app.rs"
                                  },
                                  "beginLine" : 56,
                                  "beginColumn" : 11,
                                  "endLine" : 57,
                                  "endColumn" : 258,
                                  "offset" : 2712,
                                  "length" : 259
                                }
                              ],
                              [
                                "atLeastOneZero_StructArray",
                                {
                                  "type" : "Position",
                                  "uriOpt" : {
                                    "type" : "Some",
                                    "value" : "crates\/consumer_consumer\/src\/component\/consumer_consumer_app.rs"
                                  },
                                  "beginLine" : 58,
                                  "beginColumn" : 11,
                                  "endLine" : 59,
                                  "endColumn" : 197,
                                  "offset" : 3017,
                                  "length" : 198
                                }
                              ],
                              [
                                "isSorted_ArrayInt32",
                                {
                                  "type" : "Position",
                                  "uriOpt" : {
                                    "type" : "Some",
                                    "value" : "crates\/consumer_consumer\/src\/component\/consumer_consumer_app.rs"
                                  },
                                  "beginLine" : 60,
                                  "beginColumn" : 11,
                                  "endLine" : 61,
                                  "endColumn" : 197,
                                  "offset" : 3254,
                                  "length" : 198
                                }
                              ],
                              [
                                "atLeastOneZero_ArrayInt32",
                                {
                                  "type" : "Position",
                                  "uriOpt" : {
                                    "type" : "Some",
                                    "value" : "crates\/consumer_consumer\/src\/component\/consumer_consumer_app.rs"
                                  },
                                  "beginLine" : 62,
                                  "beginColumn" : 11,
                                  "endLine" : 63,
                                  "endColumn" : 160,
                                  "offset" : 3497,
                                  "length" : 161
                                }
                              ],
                              [
                                "isSorted_ArrayStruct",
                                {
                                  "type" : "Position",
                                  "uriOpt" : {
                                    "type" : "Some",
                                    "value" : "crates\/consumer_consumer\/src\/component\/consumer_consumer_app.rs"
                                  },
                                  "beginLine" : 64,
                                  "beginColumn" : 11,
                                  "endLine" : 67,
                                  "endColumn" : 113,
                                  "offset" : 3698,
                                  "length" : 331
                                }
                              ],
                              [
                                "atLeastOneZero_ArrayStruct",
                                {
                                  "type" : "Position",
                                  "uriOpt" : {
                                    "type" : "Some",
                                    "value" : "crates\/consumer_consumer\/src\/component\/consumer_consumer_app.rs"
                                  },
                                  "beginLine" : 72,
                                  "beginColumn" : 11,
                                  "endLine" : 73,
                                  "endColumn" : 171,
                                  "offset" : 4253,
                                  "length" : 172
                                }
                              ]
                            ]
                          },
                          "guaranteesReport" : {
                            "type" : "HashSMap",
                            "size" : 1,
                            "entries" : [
                              [
                                "conversions",
                                {
                                  "type" : "Position",
                                  "uriOpt" : {
                                    "type" : "Some",
                                    "value" : "crates\/consumer_consumer\/src\/component\/consumer_consumer_app.rs"
                                  },
                                  "beginLine" : 77,
                                  "beginColumn" : 11,
                                  "endLine" : 86,
                                  "endColumn" : 26,
                                  "offset" : 4566,
                                  "length" : 292
                                }
                              ]
                            ]
                          },
                          "casesReport" : {
                            "type" : "HashSMap",
                            "size" : 0,
                            "entries" : [
                            ]
                          },
                          "handlers" : {
                            "type" : "HashSMap",
                            "size" : 0,
                            "entries" : [
                            ]
                          }
                        }
                      }
                    }
                  },
                  "gumboXReport" : {
                    "type" : "Some",
                    "value" : {
                      "type" : "org.sireum.hamr.codegen.microkit.reporting.GumboXReport",
                      "gumboxMethods" : {
                        "type" : "HashSMap",
                        "size" : 20,
                        "entries" : [
                          [
                            "convertB",
                            {
                              "type" : "Position",
                              "uriOpt" : {
                                "type" : "Some",
                                "value" : "crates\/consumer_consumer\/src\/bridge\/consumer_consumer_GUMBOX.rs"
                              },
                              "beginLine" : 17,
                              "beginColumn" : 5,
                              "endLine" : 27,
                              "endColumn" : 1,
                              "offset" : 252,
                              "length" : 262
                            }
                          ],
                          [
                            "convertS8",
                            {
                              "type" : "Position",
                              "uriOpt" : {
                                "type" : "Some",
                                "value" : "crates\/consumer_consumer\/src\/bridge\/consumer_consumer_GUMBOX.rs"
                              },
                              "beginLine" : 29,
                              "beginColumn" : 5,
                              "endLine" : 39,
                              "endColumn" : 1,
                              "offset" : 521,
                              "length" : 261
                            }
                          ],
                          [
                            "convertS16",
                            {
                              "type" : "Position",
                              "uriOpt" : {
                                "type" : "Some",
                                "value" : "crates\/consumer_consumer\/src\/bridge\/consumer_consumer_GUMBOX.rs"
                              },
                              "beginLine" : 41,
                              "beginColumn" : 5,
                              "endLine" : 51,
                              "endColumn" : 1,
                              "offset" : 789,
                              "length" : 263
                            }
                          ],
                          [
                            "convertS32",
                            {
                              "type" : "Position",
                              "uriOpt" : {
                                "type" : "Some",
                                "value" : "crates\/consumer_consumer\/src\/bridge\/consumer_consumer_GUMBOX.rs"
                              },
                              "beginLine" : 53,
                              "beginColumn" : 5,
                              "endLine" : 63,
                              "endColumn" : 1,
                              "offset" : 1059,
                              "length" : 263
                            }
                          ],
                          [
                            "convertS64",
                            {
                              "type" : "Position",
                              "uriOpt" : {
                                "type" : "Some",
                                "value" : "crates\/consumer_consumer\/src\/bridge\/consumer_consumer_GUMBOX.rs"
                              },
                              "beginLine" : 65,
                              "beginColumn" : 5,
                              "endLine" : 75,
                              "endColumn" : 1,
                              "offset" : 1329,
                              "length" : 263
                            }
                          ],
                          [
                            "convertU8",
                            {
                              "type" : "Position",
                              "uriOpt" : {
                                "type" : "Some",
                                "value" : "crates\/consumer_consumer\/src\/bridge\/consumer_consumer_GUMBOX.rs"
                              },
                              "beginLine" : 77,
                              "beginColumn" : 5,
                              "endLine" : 87,
                              "endColumn" : 1,
                              "offset" : 1599,
                              "length" : 261
                            }
                          ],
                          [
                            "convertU16",
                            {
                              "type" : "Position",
                              "uriOpt" : {
                                "type" : "Some",
                                "value" : "crates\/consumer_consumer\/src\/bridge\/consumer_consumer_GUMBOX.rs"
                              },
                              "beginLine" : 89,
                              "beginColumn" : 5,
                              "endLine" : 99,
                              "endColumn" : 1,
                              "offset" : 1867,
                              "length" : 263
                            }
                          ],
                          [
                            "convertU32",
                            {
                              "type" : "Position",
                              "uriOpt" : {
                                "type" : "Some",
                                "value" : "crates\/consumer_consumer\/src\/bridge\/consumer_consumer_GUMBOX.rs"
                              },
                              "beginLine" : 101,
                              "beginColumn" : 5,
                              "endLine" : 111,
                              "endColumn" : 1,
                              "offset" : 2137,
                              "length" : 263
                            }
                          ],
                          [
                            "convertU64",
                            {
                              "type" : "Position",
                              "uriOpt" : {
                                "type" : "Some",
                                "value" : "crates\/consumer_consumer\/src\/bridge\/consumer_consumer_GUMBOX.rs"
                              },
                              "beginLine" : 113,
                              "beginColumn" : 5,
                              "endLine" : 123,
                              "endColumn" : 1,
                              "offset" : 2407,
                              "length" : 263
                            }
                          ],
                          [
                            "compute_spec_isSorted_StructArray_assume",
                            {
                              "type" : "Position",
                              "uriOpt" : {
                                "type" : "Some",
                                "value" : "crates\/consumer_consumer\/src\/bridge\/consumer_consumer_GUMBOX.rs"
                              },
                              "beginLine" : 130,
                              "beginColumn" : 5,
                              "endLine" : 135,
                              "endColumn" : 1,
                              "offset" : 2805,
                              "length" : 345
                            }
                          ],
                          [
                            "compute_spec_atLeastOneZero_StructArray_assume",
                            {
                              "type" : "Position",
                              "uriOpt" : {
                                "type" : "Some",
                                "value" : "crates\/consumer_consumer\/src\/bridge\/consumer_consumer_GUMBOX.rs"
                              },
                              "beginLine" : 142,
                              "beginColumn" : 5,
                              "endLine" : 147,
                              "endColumn" : 1,
                              "offset" : 3291,
                              "length" : 296
                            }
                          ],
                          [
                            "compute_spec_isSorted_ArrayInt32_assume",
                            {
                              "type" : "Position",
                              "uriOpt" : {
                                "type" : "Some",
                                "value" : "crates\/consumer_consumer\/src\/bridge\/consumer_consumer_GUMBOX.rs"
                              },
                              "beginLine" : 154,
                              "beginColumn" : 5,
                              "endLine" : 159,
                              "endColumn" : 1,
                              "offset" : 3720,
                              "length" : 279
                            }
                          ],
                          [
                            "compute_spec_atLeastOneZero_ArrayInt32_assume",
                            {
                              "type" : "Position",
                              "uriOpt" : {
                                "type" : "Some",
                                "value" : "crates\/consumer_consumer\/src\/bridge\/consumer_consumer_GUMBOX.rs"
                              },
                              "beginLine" : 166,
                              "beginColumn" : 5,
                              "endLine" : 171,
                              "endColumn" : 1,
                              "offset" : 4138,
                              "length" : 254
                            }
                          ],
                          [
                            "compute_spec_isSorted_ArrayStruct_assume",
                            {
                              "type" : "Position",
                              "uriOpt" : {
                                "type" : "Some",
                                "value" : "crates\/consumer_consumer\/src\/bridge\/consumer_consumer_GUMBOX.rs"
                              },
                              "beginLine" : 180,
                              "beginColumn" : 5,
                              "endLine" : 189,
                              "endColumn" : 1,
                              "offset" : 4730,
                              "length" : 360
                            }
                          ],
                          [
                            "compute_spec_atLeastOneZero_ArrayStruct_assume",
                            {
                              "type" : "Position",
                              "uriOpt" : {
                                "type" : "Some",
                                "value" : "crates\/consumer_consumer\/src\/bridge\/consumer_consumer_GUMBOX.rs"
                              },
                              "beginLine" : 196,
                              "beginColumn" : 5,
                              "endLine" : 201,
                              "endColumn" : 1,
                              "offset" : 5231,
                              "length" : 268
                            }
                          ],
                          [
                            "compute_CEP_T_Assm",
                            {
                              "type" : "Position",
                              "uriOpt" : {
                                "type" : "Some",
                                "value" : "crates\/consumer_consumer\/src\/bridge\/consumer_consumer_GUMBOX.rs"
                              },
                              "beginLine" : 209,
                              "beginColumn" : 5,
                              "endLine" : 222,
                              "endColumn" : 1,
                              "offset" : 5753,
                              "length" : 757
                            }
                          ],
                          [
                            "compute_CEP_Pre",
                            {
                              "type" : "Position",
                              "uriOpt" : {
                                "type" : "Some",
                                "value" : "crates\/consumer_consumer\/src\/bridge\/consumer_consumer_GUMBOX.rs"
                              },
                              "beginLine" : 230,
                              "beginColumn" : 5,
                              "endLine" : 239,
                              "endColumn" : 1,
                              "offset" : 6746,
                              "length" : 398
                            }
                          ],
                          [
                            "compute_spec_conversions_guarantee",
                            {
                              "type" : "Position",
                              "uriOpt" : {
                                "type" : "Some",
                                "value" : "crates\/consumer_consumer\/src\/bridge\/consumer_consumer_GUMBOX.rs"
                              },
                              "beginLine" : 246,
                              "beginColumn" : 5,
                              "endLine" : 256,
                              "endColumn" : 1,
                              "offset" : 7254,
                              "length" : 251
                            }
                          ],
                          [
                            "compute_CEP_T_Guar",
                            {
                              "type" : "Position",
                              "uriOpt" : {
                                "type" : "Some",
                                "value" : "crates\/consumer_consumer\/src\/bridge\/consumer_consumer_GUMBOX.rs"
                              },
                              "beginLine" : 261,
                              "beginColumn" : 5,
                              "endLine" : 266,
                              "endColumn" : 1,
                              "offset" : 7601,
                              "length" : 103
                            }
                          ],
                          [
                            "compute_CEP_Post",
                            {
                              "type" : "Position",
                              "uriOpt" : {
                                "type" : "Some",
                                "value" : "crates\/consumer_consumer\/src\/bridge\/consumer_consumer_GUMBOX.rs"
                              },
                              "beginLine" : 274,
                              "beginColumn" : 5,
                              "endLine" : 283,
                              "endColumn" : 1,
                              "offset" : 7942,
                              "length" : 348
                            }
                          ]
                        ]
                      }
                    }
                  }
                }
              ]
            ]
          }
        }
      ]
    ]
  }
}